setup.py
spine_python.egg-info/PKG-INFO
spine_python.egg-info/SOURCES.txt
spine_python.egg-info/dependency_links.txt
spine_python.egg-info/top_level.txt
src/Attachment.py
src/AttachmentLoader.py
src/Bone.py
src/BoneData.py
src/Enum.py
src/RegionAttachment.py
src/Skeleton.py
src/SkeletonData.py
src/SkeletonJson.py
src/Skin.py
src/Slot.py
src/SlotData.py
src/__init__.py
src/Animation/Timeline.py
src/Animation/__init__.py
src/Atlas/AtlasPage.py
src/Atlas/AtlasRegion.py
src/Atlas/__init__.py