Metadata-Version: 1.0
Name: spine-python
Version: 1.0b2
Summary: A Pure Python Spine runtime.
Home-page: https://github.com/terrysimons/spine-python/spine-python
Author: Terry Simons
Author-email: terry.simons@gmail.com
License: UNKNOWN
Platform: UNKNOWN
Classifier: License :: OSI Approved :: BSD License
